nr_packaging_test/__init__.py
nr_packaging_test-0.1.0.dist-info/METADATA
nr_packaging_test-0.1.0.dist-info/WHEEL
nr_packaging_test-0.1.0.dist-info/top_level.txt
nr_packaging_test-0.1.0.dist-info/zip-safe
nr_packaging_test-0.1.0.dist-info/RECORD
