Metadata-Version: 2.1
Name: nr-packaging-test
Version: 0.1.0
Summary: Package description here.
Home-page: UNKNOWN
Author: Niklas Rosenstein
Author-email: rosensteinniklas@gmail.com
License: UNKNOWN
Platform: UNKNOWN
Requires-Python: >=3.5.0,<4.0.0
Requires-Dist: dataclasses (<1.0.0,>=0.6.0)
